sympy_equation-1.2.0.dist-info/METADATA
sympy_equation-1.2.0.dist-info/WHEEL
sympy_equation-1.2.0.dist-info/entry_points.txt
sympy_equation/__init__.py
sympy_equation/algebraic_equation.py
sympy_equation/preparser.py
sympy_equation/utils.py
sympy_equation-1.2.0.dist-info/RECORD
