Metadata-Version: 2.1
Name: sympy_equation
Version: 1.2.0
Summary: Equations that can be algebraicly manipulated.
Keywords: symbolic algebra,computer algebra,CAS,sympy,equation
Author-Email: =?utf-8?q?Davide_Sandon=C3=A0?= <sandona.davide@gmail.com>, Jonathan Gutow <gutow@uwosh.edu>
License: GPL-3.0+
Classifier: Development Status :: 5 - Production/Stable
Classifier: Intended Audience :: Developers
Classifier: Intended Audience :: Education
Classifier: Intended Audience :: End Users/Desktop
Classifier: License :: OSI Approved :: GNU General Public License v3 or later (GPLv3+)
Classifier: Operating System :: OS Independent
Classifier: Programming Language :: Python :: 3
Project-URL: Homepage, https://github.com/Davide-sd/sympy-equation
Requires-Python: >=3.9
Requires-Dist: param
Requires-Dist: sympy
Provides-Extra: interactive
Requires-Dist: ipython>=8.18.1; extra == "interactive"
Requires-Dist: jupyterlab>=4.4.2; extra == "interactive"
